{"5/OL6jlAhzqfYW3dBiJ7Zw==":"speial-selections-2.png","iDXdVgBqDhoiheHUSvuuSA==":"speial-selections-3.png","3+455kGNsGmITeDJ7QqAJw==":"canva-coffee-ring-stain.png","ay8GrTQ68PtRIBqYd+6YHA==":"speial-selections-4.png","6u/ZTWbX5PPzxuWmmDutqA==":"coffee-brewing-how-to-pour-over-french-press-local-milk-blog.jpeg","WYNabhy2DT6NDCUiMZ0/FA==":"carolina-tognon-on-instagram-bom-dia-but-first-coffee-quem-ai-e-viciado-.jpeg","KINeZIa1e5Lhg0jXMRWiWg==":"coffee-brewing-how-to-pour-over-french-press-local-milk-blog-1.jpeg","/09mJQ8Pqo6dSFaC6usADA==":"gosto-disto.jpeg","QbHC4dzKiG4okx3FijOugw==":"cafe-forte-x-cafe-fraco-1.jpeg","WOzu9fqJsBJp5T2sX09DCA==":"canva-white-mug-near-book.jpg","GoKJOBUQQtXVwR0V/4qfkQ==":"canva-person-holding-latte-cup.jpg","u6VtNlKYWf9z9S0z10ZhPw==":"cafe-forte-x-cafe-fraco-2.jpeg","xLh9EuABBdY2tMkLVZLE5w==":"-.jpeg","XmY668e78rgmRT3akY1guw==":"--1.jpeg","0X0XEPKyCqwxfz1pdimAAw==":"--2.jpeg","+XFFYj31I97yuCIcFgyv4A==":"optxmist-on-we-heart-it.jpeg","u66RbbvSLX63PVoYtkzCAw==":"loading-.jpeg"}